<?xml version="1.0"?>
<block>
  <name>hermesWB</name>
  <key>hpsdr_hermesWB</key>
  <category>hpsdr</category>
  <import>import hpsdr</import>
  <make>hpsdr.hermesWB($RxPre, $Intfc, $CkS, $AlexRA, $AlexTA, $AlexHPF, $AlexLPF)</make>
  <callback>set_RxPreamp($RxPre)</callback>
  <callback>set_ClockSource($CkS)</callback>
  <callback>set_AlexRxAntenna($AlexRA)</callback>
  <callback>set_AlexTxAntenna($AlexTA)</callback>
  <callback>set_AlexRxHPF($AlexHPF)</callback>
  <callback>set_AlexTxLPF($AlexLPF)</callback>
 <!-- Make one 'param' node for every Parameter you want settable from the GUI.
       Sub-nodes:
       * name
       * key (makes the value accessible as $keyname, e.g. in the make node)
       * type -->
  <param>
    <name>Rx Preamp Off/On</name>
    <key>RxPre</key>
    <value>0</value>
    <type>int</type>
  </param>
  <param>
    <name>Ethernet Interface</name>
    <key>Intfc</key>
    <value>"eth0"</value>
    <type>raw</type>
  </param>
  <param>
    <name>HPSDR Clock Source</name>
    <key>CkS</key>
    <value>"0xF8"</value>
    <type>raw</type>
  </param>
  <param>
    <name>Alex Tx Antenna</name>
    <key>AlexTA</key>
    <value>0</value>
    <type>enum</type>
    <option>
      <name>Tx1</name>
      <key>0</key>
    </option>
    <option>
      <name>Tx2</name>
      <key>1</key>
    </option>
    <option>
      <name>Tx3</name>
      <key>2</key>
    </option>
  </param>
  <param>
    <name>Alex Rx Antenna</name>
    <key>AlexRA</key>
    <value>0</value>
    <type>enum</type>
    <option>
      <name>Tx Ant via T/R Relay</name>
      <key>0</key>
    </option>
    <option>
      <name>Rx1</name>
      <key>0xa0</key>
    </option>
    <option>
      <name>Rx2</name>
      <key>0xc0</key>
    </option>
    <option>
      <name>RxXvrtr</name>
      <key>0xe0</key>
    </option>
  </param>
  <param>
    <name>Alex Rx HPF</name>
    <key>AlexHPF</key>
    <value>0x20</value>
    <type>enum</type>
     <option>
      <name>Bypass</name>
      <key>0x20</key>
    </option>
    <option>
      <name>1.5 MHz HPF</name>
      <key>0x10</key>
    </option>
    <option>
      <name>6.5 MHz HPF</name>
      <key>0x08</key>
    </option>
    <option>
      <name>9.5 MHz HPF</name>
      <key>0x04</key>
    </option>
    <option>
      <name>13 MHz HPF</name>
      <key>0x01</key>
    </option>
    <option>
      <name>20 MHz HPF</name>
      <key>0x02</key>
    </option>
    <option>
      <name>6M LNA+LPF</name>
      <key>0x40</key>
    </option>
  </param>
  <param>
    <name>Alex Tx LPF</name>
    <key>AlexLPF</key>
    <value>0x10</value>
    <type>enum</type>
    <option>
      <name>160m LPF</name>
      <key>0x08</key>
    </option>
    <option>
      <name>80m LPF</name>
      <key>0x04</key>
    </option>
    <option>
      <name>60/40m LPF</name>
      <key>0x02</key>
    </option>
    <option>
      <name>30/20m LPF</name>
      <key>0x01</key>
    </option>
    <option>
      <name>17/15m LPF</name>
      <key>0x40</key>
    </option>
    <option>
      <name>12/10m LPF</name>
      <key>0x20</key>
    </option>
    <option>
      <name>6m LPF</name>
      <key>0x10</key>
    </option>
  </param>


  <!-- Make one 'sink' node per input. Sub-nodes:
       * name (an identifier for the GUI)
       * type
       * vlen
       * optional (set to 1 for optional inputs) -->
  <!-- <sink>
    <name>in</name>
    <type>complex</type>
  </sink> -->

  <!-- Make one 'source' node per output. Sub-nodes:
       * name (an identifier for the GUI)
       * type e.g.   int, real, complex, byte, short, xxx_vector, ...
       * vlen
       * optional (set to 1 for optional inputs) -->
  <source>
    <name>out</name>
    <type>float</type>
    <vlen>16384</vlen>
  </source>

  <doc>
  This block is the HPSDR Hermes/Metis wideband module.
  It supports one wideband sampled receiver which outputs a vector
  of 16384 time-continuous real float samples sampled at 122.88 MHz.
  Consecutive vectors ARE NOT time contiguous. The update rates is a
  few vectors per second.
  *RxPreamp = 0 (Off), or  1 (On)
  *Interface = the ethernet interface to use.
    Example: "eth0" {including quote marks}.
  *Clock Source = HPSDR Clock Selector - 1 byte-> assigned to one register.
  byte->C1 when C0 = 0. Allows selection of clock and mic sources. Only upper
  6 bits are used (lower 2 bits are overwritten by receive sample speed
  selection. Hermes ignores this register. Default value selects Mercury.
    Example: "0xfc" {including quote marks}
  *Alex Tx Ant = selects transmit antenna (Tx1, Tx2, or Tx3).
  *Alex Rx ant = selects receive antenna connector, or Tx antenna via T/R relay.
  *Alex Tx LPF = selects Low Pass Filter.
  *Alex Rx HPF = selects receive High Pass Filter.
  </doc>
</block>
